wespe/__init__.py
wespe/exceptions.py
wespe/batch_uploaders/__init__.py
wespe/batch_uploaders/facebook.py
wespe/batch_uploaders/requests.py
wespe/batch_uploaders/facebook/__init__.py
wespe/batch_uploaders/facebook/facebook_batch.py
wespe/batch_uploaders/facebook/facebook_batch_request_error.py
wespe/batch_uploaders/facebook/facebook_batch_response.py
wespe/batch_uploaders/facebook/facebook_batch_uploader.py
wespe/batch_uploaders/facebook/retries.py
wespe-0.2.1.dist-info/DESCRIPTION.rst
wespe-0.2.1.dist-info/METADATA
wespe-0.2.1.dist-info/RECORD
wespe-0.2.1.dist-info/WHEEL
wespe-0.2.1.dist-info/metadata.json
wespe-0.2.1.dist-info/top_level.txt
