Metadata-Version: 2.0
Name: wespe
Version: 0.2.1
Summary: Batching ad tech providers’ operations for humans
Home-page: https://github.com/kayak/wespe
Author: Lucas Lira Gomes
Author-email: llira@kayak.com
License: UNKNOWN
Keywords: wespe adtech marketing facebook google bing yandex facebook
Platform: UNKNOWN
Classifier: License :: OSI Approved :: Apache Software License
Classifier: Development Status :: 5 - Production/Stable
Classifier: Intended Audience :: Developers
Classifier: Natural Language :: English
Classifier: Programming Language :: Python :: 3
Classifier: Programming Language :: Python :: 3.6
Classifier: Programming Language :: Python :: 3.7
Requires-Dist: facebook-business (==5.0.4)
Requires-Dist: requests (==2.22.0)
Requires-Dist: tenacity (==5.0.2)
Requires-Dist: typing (==3.7.4.1)
